{
  "schemaVersion": 1,
  "version": "1.0.0-beta.3.12",
  "tag": "v1.0.0-beta.3.12",
  "gitSha": "ec66514431c4ec09cad0c0370bada758a7432463",
  "releaseDate": "2026-07-06",
  "channel": "beta.3",
  "releaseNotes": {
    "version": "1.0.0-beta.3.12",
    "date": "2026-07-06",
    "noticeId": "2026-07-06-v1.0.0-beta.3.12",
    "showPopup": true,
    "added": [
      "archive Xinlongtai preview PDFs"
    ],
    "improved": [],
    "fixed": [],
    "modules": []
  },
  "announcement": {
    "noticeId": "v1.0.0-beta.3.12",
    "version": "1.0.0-beta.3.12",
    "releaseDate": "2026-07-06",
    "showPopup": true,
    "level": "feature",
    "title": "本次更新内容",
    "groups": [
      {
        "title": "新增",
        "icon": "sparkles",
        "items": [
          "archive Xinlongtai preview PDFs"
        ]
      }
    ]
  },
  "artifacts": {
    "serverPackage": null,
    "desktopInstaller": null,
    "desktopFullInstaller": null,
    "automationHelper": null
  }
}
